kf_d3m_primitives/__init__.py
kf_d3m_primitives/pipeline_base.py
kf_d3m_primitives/clustering/__init__.py
kf_d3m_primitives/clustering/hdbscan/Hdbscan.py
kf_d3m_primitives/clustering/hdbscan/__init__.py
kf_d3m_primitives/clustering/hdbscan/hdbscan_pipeline.py
kf_d3m_primitives/clustering/k_means/Storc.py
kf_d3m_primitives/clustering/k_means/__init__.py
kf_d3m_primitives/clustering/k_means/storc_pipeline.py
kf_d3m_primitives/clustering/k_means/test/__init__.py
kf_d3m_primitives/clustering/k_means/test/test_sloth.py
kf_d3m_primitives/clustering/k_means/test/utils.py
kf_d3m_primitives/clustering/spectral_clustering/__init__.py
kf_d3m_primitives/clustering/spectral_clustering/spectral_clustering.py
kf_d3m_primitives/clustering/spectral_clustering/spectral_clustering_pipeline.py
kf_d3m_primitives/clustering/utils/__init__.py
kf_d3m_primitives/clustering/utils/cluster.py
kf_d3m_primitives/clustering/utils/dataframe_utils.py
kf_d3m_primitives/data_preprocessing/__init__.py
kf_d3m_primitives/data_preprocessing/data_cleaning/__init__.py
kf_d3m_primitives/data_preprocessing/data_cleaning/data_cleaning.py
kf_d3m_primitives/data_preprocessing/data_cleaning/data_cleaning_pipeline.py
kf_d3m_primitives/data_preprocessing/data_typing/__init__.py
kf_d3m_primitives/data_preprocessing/data_typing/simon.py
kf_d3m_primitives/data_preprocessing/data_typing/simon_pipeline.py
kf_d3m_primitives/data_preprocessing/geocoding_forward/__init__.py
kf_d3m_primitives/data_preprocessing/geocoding_forward/goat_forward.py
kf_d3m_primitives/data_preprocessing/geocoding_forward/goat_forward_pipeline.py
kf_d3m_primitives/data_preprocessing/geocoding_reverse/__init__.py
kf_d3m_primitives/data_preprocessing/geocoding_reverse/goat_reverse.py
kf_d3m_primitives/data_preprocessing/geocoding_reverse/goat_reverse_pipeline.py
kf_d3m_primitives/data_preprocessing/text_summarization/__init__.py
kf_d3m_primitives/data_preprocessing/text_summarization/duke.py
kf_d3m_primitives-0.6.4.dist-info/LICENSE
kf_d3m_primitives-0.6.4.dist-info/METADATA
kf_d3m_primitives-0.6.4.dist-info/WHEEL
kf_d3m_primitives-0.6.4.dist-info/entry_points.txt
kf_d3m_primitives-0.6.4.dist-info/top_level.txt
kf_d3m_primitives-0.6.4.dist-info/RECORD
