Metadata-Version: 2.1
Name: kf-d3m-primitives
Version: 0.6.4
Summary: All Kung Fu D3M primitives as a single library
Home-page: https://gitlab.com/datadrivendiscovery/contrib/kungfuai-primitives
License: Apache-2.0
Keywords: d3m_primitive
License-File: LICENSE
Requires-Dist: d3m
Requires-Dist: torch (>=1.4.0)
Requires-Dist: pillow (==7.1.2)
Requires-Dist: tslearn (==0.4.1)
Requires-Dist: statsmodels (==0.11.1)
Requires-Dist: pmdarima (==1.8.1)
Requires-Dist: hdbscan (<0.9,>=0.8.26)
Requires-Dist: requests (==2.23.0)
Requires-Dist: shap (==0.37.0)
Requires-Dist: torchvision (>=0.5.0)
Requires-Dist: opencv-python-headless (<5,>=4.1)
Requires-Dist: gluonts (==0.6.0)
Requires-Dist: albumentations (==0.4.6)
Requires-Dist: tifffile (==2020.8.13)
Requires-Dist: tqdm (==4.48.2)
Requires-Dist: d3m-segmentation-models-pytorch (==0.1.3)
Requires-Dist: lz4 (==3.1.3)
Requires-Dist: faiss-cpu (<1.8)
Requires-Dist: punkML (<4.0.0,>=3.0.1)
Requires-Dist: object-detection-retinanet (<0.3,>=0.1)
Requires-Dist: d3m-simon (<1.3,>=1.2)
Requires-Dist: nk-sent2vec (<1.5,>=1.4)
Requires-Dist: d3m-duke (<1.3.0,>=1.2.0)
Requires-Dist: d3m-remote-sensing-pretrained (<1.1,>=1.0)
Provides-Extra: cpu
Requires-Dist: tensorflow (==2.2.0) ; extra == 'cpu'
Requires-Dist: mxnet (==1.6.0) ; extra == 'cpu'
Requires-Dist: d3m-simon[cpu] ; extra == 'cpu'
Provides-Extra: gpu-cuda-10.1
Requires-Dist: tensorflow-gpu (==2.2.0) ; extra == 'gpu-cuda-10.1'
Requires-Dist: mxnet-cu101mkl (==1.6.0.post0) ; extra == 'gpu-cuda-10.1'
Requires-Dist: d3m-simon[gpu] ; extra == 'gpu-cuda-10.1'
Provides-Extra: gpu-cuda-9.2
Requires-Dist: tensorflow-gpu (==2.2.0) ; extra == 'gpu-cuda-9.2'
Requires-Dist: mxnet-cu92mkl (==1.6.0.post0) ; extra == 'gpu-cuda-9.2'
Requires-Dist: d3m-simon[gpu] ; extra == 'gpu-cuda-9.2'
